ct4/__init__.py
ct4/__main__.py
ct4-0.0.2.dist-info/LICENSE
ct4-0.0.2.dist-info/METADATA
ct4-0.0.2.dist-info/WHEEL
ct4-0.0.2.dist-info/top_level.txt
ct4-0.0.2.dist-info/RECORD
