Metadata-Version: 2.1
Name: ct4
Version: 0.0.2
Summary: Create Template Command Line
Author-email: RMayorgaV <rmayorgav@rmayorgav.com>
Project-URL: Homepage, https://github.com/rmayorgav/ct4
Project-URL: Issues, https://github.com/rmayorgav/ct4/issues
Classifier: Programming Language :: Python :: 3
Classifier: License :: OSI Approved :: Apache Software License
Classifier: Operating System :: OS Independent
Requires-Python: >=3.8
License-File: LICENSE
